AUTHORS.rst
LICENSE
README.md
setup.py
DesOptPy/DesOptPy.py
DesOptPy/DesOptPy.workingpy
DesOptPy/DesOptPyYafl.py
DesOptPy/DesOptPy_old.py
DesOptPy/FunctionAggregation.py
DesOptPy/Monitor.py
DesOptPy/RangeConstraint.py
DesOptPy/__init__.py
DesOptPy/hist2.png
DesOptPy/plotting.py
DesOptPy/postprocessingNumerical.py
DesOptPy/printing.py
DesOptPy/pyOptTools.py
DesOptPy/scaling.py
DesOptPy/tools.py
DesOptPy.egg-info/PKG-INFO
DesOptPy.egg-info/SOURCES.txt
DesOptPy.egg-info/dependency_links.txt
DesOptPy.egg-info/top_level.txt
DesOptPy/__pycache__/DesOptPy.cpython-39.pyc
DesOptPy/__pycache__/DesOptPy_old.cpython-39.pyc
DesOptPy/__pycache__/FunctionAggregation.cpython-39.pyc
DesOptPy/__pycache__/PostprocessingNumerical.cpython-39.pyc
DesOptPy/__pycache__/RangeConstraint.cpython-39.pyc
DesOptPy/__pycache__/SciPy.cpython-39.pyc
DesOptPy/__pycache__/__init__.cpython-39.pyc
DesOptPy/__pycache__/plotting.cpython-39.pyc
DesOptPy/__pycache__/postprocessingNumerical.cpython-39.pyc
DesOptPy/__pycache__/printing.cpython-39.pyc
DesOptPy/__pycache__/pyOptTools.cpython-39.pyc
DesOptPy/__pycache__/scaling.cpython-39.pyc
DesOptPy/__pycache__/tools.cpython-39.pyc
DesOptPy/interfaces/CvxOpt.py
DesOptPy/interfaces/Deap.py
DesOptPy/interfaces/NlOpt.py
DesOptPy/interfaces/PyGmo.py
DesOptPy/interfaces/SciPy.py
DesOptPy/interfaces/unbenannt1.py
DesOptPy/interfaces/__pycache__/NlOpt.cpython-39.pyc
DesOptPy/interfaces/__pycache__/PyGmo.cpython-39.pyc
DesOptPy/interfaces/__pycache__/SciPy.cpython-39.pyc
DesOptPy/optimizers/hca.py
examples/CantileverAllEasyBeam.py
examples/CantileverEasyBeam.py
examples/TestProblemsConstrained/Cantilever.py
examples/TestProblemsConstrained/CylinderHead.py
examples/TestProblemsConstrained/CylinderHead2.py
examples/TestProblemsConstrained/Portfolio.py
examples/TestProblemsConstrained/TP037.py
examples/TestProblemsConstrained/Textbook.py
examples/TestProblemsUnconstrained/Ackley.py
examples/TestProblemsUnconstrained/DixonPrice.py
examples/TestProblemsUnconstrained/Eggholder.py
examples/TestProblemsUnconstrained/Griewank.py
examples/TestProblemsUnconstrained/Himmelblau.py
