Metadata-Version: 2.1
Name: DesOptPy
Version: 2022.1.5
Summary: DESign OPTimization in PYthon
Home-page: https://github.com/e-dub/DesOptPy
Author: E. J. Wehrle
Author-email: Erich.Wehrle@unibz.it
License: GNU Lesser General Public License 3.0
Platform: UNKNOWN
License-File: LICENSE
License-File: AUTHORS.rst
